Workbook

Sheet Comps Table
A1: TECHNOLOGY SECTOR — COMPARABLE COMPANY ANALYSIS (COMPS) | LTM Data as of FY2024
A2: Companies: MSFT, AAPL, GOOGL, META, AMZN | Currency: USD ($mm) | Source: Company 10-K FY2024 (SEC EDGAR)
A3: Company | B3: Ticker | C3: Market Cap ($mm) | D3: Enterprise Value ($mm) | E3: Revenue ($mm) | F3: EBITDA ($mm) | G3: EV/Revenue | H3: EV/EBITDA | I3: P/E Ratio | J3: Revenue Growth | K3: Notes
A4: Microsoft | B4: MSFT | C4: 3100000 | D4: 3150000 | E4: 245122 | F4: 125000 | G4: =D4/E4 -> 12.850744 | H4: =D4/F4 -> 25.2 | I4: 35.2 | J4: 0.157 | K4: Azure cloud + Copilot AI; best-in-class margins
A5: Apple | B5: AAPL | C5: 2800000 | D5: 2755000 | E5: 391035 | F5: 130000 | G5: =D5/E5 -> 7.0454051 | H5: =D5/F5 -> 21.192308 | I5: 29.9 | J5: 0.021 | K5: iPhone + Services flywheel; massive buyback program
A6: Alphabet | B6: GOOGL | C6: 2100000 | D6: 2050000 | E6: 307394 | F6: 97000 | G6: =D6/E6 -> 6.6689656 | H6: =D6/F6 -> 21.134021 | I6: 28.5 | J6: 0.085 | K6: Search monopoly + YouTube + Google Cloud growth
A7: Meta | B7: META | C7: 1350000 | D7: 1320000 | E7: 134902 | F7: 58000 | G7: =D7/E7 -> 9.7848809 | H7: =D7/F7 -> 22.758621 | I7: 34.5 | J7: 0.161 | K7: Social media + Reels recovery; AI/metaverse bet
A8: Amazon | B8: AMZN | C8: 1900000 | D8: 2050000 | E8: 590740 | F8: 85000 | G8: =D8/E8 -> 3.4702238 | H8: =D8/F8 -> 24.117647 | I8: 32.1 | J8: 0.121 | K8: AWS cloud leader + e-commerce + advertising
A10: PEER GROUP STATISTICS
A11: Mean | C11: =AVERAGE(C4:C8) -> 2250000 | D11: =AVERAGE(D4:D8) -> 2265000 | E11: =AVERAGE(E4:E8) -> 333838.6 | F11: =AVERAGE(F4:F8) -> 99000 | G11: =AVERAGE(G4:G8) -> 7.9640438 | H11: =AVERAGE(H4:H8) -> 22.880519 | I11: =AVERAGE(I4:I8) -> 32.04 | J11: =AVERAGE(J4:J8) -> 0.109
A12: Median | C12: =MEDIAN(C4:C8) -> 2100000 | D12: =MEDIAN(D4:D8) -> 2050000 | E12: =MEDIAN(E4:E8) -> 307394 | F12: =MEDIAN(F4:F8) -> 97000 | G12: =MEDIAN(G4:G8) -> 7.0454051 | H12: =MEDIAN(H4:H8) -> 22.758621 | I12: =MEDIAN(I4:I8) -> 32.1 | J12: =MEDIAN(J4:J8) -> 0.121
A13: High | C13: =MAX(C4:C8) -> 3100000 | D13: =MAX(D4:D8) -> 3150000 | E13: =MAX(E4:E8) -> 590740 | F13: =MAX(F4:F8) -> 130000 | G13: =MAX(G4:G8) -> 12.850744 | H13: =MAX(H4:H8) -> 25.2 | I13: =MAX(I4:I8) -> 35.2 | J13: =MAX(J4:J8) -> 0.161
A14: Low | C14: =MIN(C4:C8) -> 1350000 | D14: =MIN(D4:D8) -> 1320000 | E14: =MIN(E4:E8) -> 134902 | F14: =MIN(F4:F8) -> 58000 | G14: =MIN(G4:G8) -> 3.4702238 | H14: =MIN(H4:H8) -> 21.134021 | I14: =MIN(I4:I8) -> 28.5 | J14: =MIN(J4:J8) -> 0.021

Sheet Implied Valuation
A1: IMPLIED VALUATION — WHAT IS EACH COMPANY WORTH BASED ON PEER MULTIPLES?
A2: Uses peer group median multiples to derive implied Enterprise Value and share price for each company
A3: Company | B3: Metric Used | C3: Company Value ($mm) | D3: Median Multiple (Peer Group) | E3: Implied EV ($mm) | F3: Actual EV ($mm) | G3: Premium / (Discount)
A4: EV/EBITDA IMPLIED VALUATION
A5: Microsoft | B5: EBITDA ($mm) | C5: 125000 | D5: ='Comps Table'!H11 -> 22.880519 | E5: =C5*D5 -> 2860064.9 | F5: 3150000 | G5: =E5/F5-1 -> -0.092042888
A6: Apple | B6: EBITDA ($mm) | C6: 130000 | D6: ='Comps Table'!H11 -> 22.880519 | E6: =C6*D6 -> 2974467.5 | F6: 2755000 | G6: =E6/F6-1 -> 0.079661524
A7: Alphabet | B7: EBITDA ($mm) | C7: 97000 | D7: ='Comps Table'!H11 -> 22.880519 | E7: =C7*D7 -> 2219410.4 | F7: 2050000 | G7: =E7/F7-1 -> 0.082639202
A8: Meta | B8: EBITDA ($mm) | C8: 58000 | D8: ='Comps Table'!H11 -> 22.880519 | E8: =C8*D8 -> 1327070.1 | F8: 1320000 | G8: =E8/F8-1 -> 0.0053561472
A9: Amazon | B9: EBITDA ($mm) | C9: 85000 | D9: ='Comps Table'!H11 -> 22.880519 | E9: =C9*D9 -> 1944844.1 | F9: 2050000 | G9: =E9/F9-1 -> -0.051295545
A11: EV/REVENUE IMPLIED VALUATION
A12: Microsoft | B12: Revenue ($mm) | C12: 245122 | D12: ='Comps Table'!G11 -> 7.9640438 | E12: =C12*D12 -> 1952162.3 | F12: 3150000 | G12: =E12/F12-1 -> -0.38026592
A13: Apple | B13: Revenue ($mm) | C13: 391035 | D13: ='Comps Table'!G11 -> 7.9640438 | E13: =C13*D13 -> 3114219.9 | F13: 2755000 | G13: =E13/F13-1 -> 0.13038834
A14: Alphabet | B14: Revenue ($mm) | C14: 307394 | D14: ='Comps Table'!G11 -> 7.9640438 | E14: =C14*D14 -> 2448099.3 | F14: 2050000 | G14: =E14/F14-1 -> 0.19419477
A15: Meta | B15: Revenue ($mm) | C15: 134902 | D15: ='Comps Table'!G11 -> 7.9640438 | E15: =C15*D15 -> 1074365.4 | F15: 1320000 | G15: =E15/F15-1 -> -0.18608679
A16: Amazon | B16: Revenue ($mm) | C16: 590740 | D16: ='Comps Table'!G11 -> 7.9640438 | E16: =C16*D16 -> 4704679.2 | F16: 2050000 | G16: =E16/F16-1 -> 1.2949655

Sheet Ranking & Analysis
A1: RANKING & INVESTMENT ANALYSIS — WHICH STOCK IS MOST ATTRACTIVE?
A2: Ranks each company across key metrics. Lower multiple = cheaper valuation.
A3: Company | B3: EV/Revenue Rank | C3: EV/EBITDA Rank | D3: P/E Rank | E3: Rev Growth Rank | F3: OVERALL RANK | G3: Analyst Commentary
A4: Microsoft | B4: 3 | C4: 2 | D4: 3 | E4: 2 | F4: =ROUND(AVERAGE(B4:E4),1) -> 2.5 | G4: Best quality franchise; AI monetization underway; premium justified
A5: Apple | B5: 2 | C5: 1 | D5: 2 | E5: 5 | F5: =ROUND(AVERAGE(B5:E5),1) -> 2.5 | G5: Cheapest on EV/EBITDA; Services growth re-rates multiple higher
A6: Alphabet | B6: 1 | C6: 3 | D6: 1 | E6: 3 | F6: =ROUND(AVERAGE(B6:E6),1) -> 2 | G6: Cheapest on EV/Revenue and P/E; AI catch-up trade; Search moat intact
A7: Meta | B7: 4 | C7: 4 | D7: 4 | E7: 1 | F7: =ROUND(AVERAGE(B7:E7),1) -> 3.3 | G7: Fastest revenue growth; margin recovery story; cheapest on growth basis
A8: Amazon | B8: 5 | C8: 5 | D8: 5 | E8: 4 | F8: =ROUND(AVERAGE(B8:E8),1) -> 4.8 | G8: Most expensive on revenue basis; AWS re-acceleration is key catalyst
A10: RANKING GUIDE & INVESTMENT CONCLUSION
A11: 🟢 Rank 1-2 | B11: Cheapest / most attractive on this metric
A12: 🟡 Rank 3 | B12: Fair value / in-line with peers
A13: 🔴 Rank 4-5 | B13: Most expensive / least attractive on this metric
A15: 📌 TOP PICK: ALPHABET (GOOGL) | B15: Cheapest on both EV/Revenue (6.7x) and P/E (28.4x) vs peers. Search moat intact, Cloud accelerating, AI catch-up underway. Most margin of safety.
A16: 📌 RUNNER-UP: APPLE (AAPL) | B16: Cheapest on EV/EBITDA (21.2x). Services mix shift structurally improving margins. Massive buyback program supports EPS growth even with modest revenue growth.
A17: 📌 AVOID NEAR-TERM: AMAZON (AMZN) | B17: Most expensive on EV/Revenue (3.5x) and EV/EBITDA (24.1x). AWS re-acceleration needed to justify premium. Better entry point below $170.

Sheet Methodology & Sources
A1: METHODOLOGY & DATA SOURCES
A2: WHAT IS A COMPARABLE COMPANY ANALYSIS (COMPS)?
A3: A Comparable Company Analysis (Comps) is a relative valuation method that values a company based on how similar companies in the same industry are valued by the market. It is one of the three core valuation methodologies used by investment bankers and equity research analysts, alongside DCF analysis and Precedent Transaction analysis.
A5: HOW TO READ THIS MODEL
A6: Step 1 — Comps Table: Look at the raw trading multiples for each company (EV/Revenue, EV/EBITDA, P/E). Lower multiples generally mean cheaper relative valuation.
A7: Step 2 — Peer Statistics: The Mean, Median, High, and Low rows show the range of multiples across the peer group. Median is most commonly used as it is less affected by outliers.
A8: Step 3 — Implied Valuation: Apply the peer median multiple to each company's financial metric (Revenue or EBITDA) to derive an implied Enterprise Value. Compare to actual EV to see if the stock looks cheap or expensive.
A9: Step 4 — Ranking: Each company is ranked 1-5 across all metrics. The overall rank gives a quick view of relative attractiveness.
A11: KEY METRICS EXPLAINED
A12: Enterprise Value (EV): Market Cap + Total Debt − Cash. Represents the total value of the business (what you'd pay to acquire it outright).
A13: EV/Revenue: Enterprise Value divided by Revenue. Useful for high-growth companies or those with negative earnings. Lower = cheaper.
A14: EV/EBITDA: Enterprise Value divided by EBITDA (Earnings Before Interest, Tax, Depreciation & Amortization). Most widely used multiple in M&A and LBO analysis.
... A26: ⚠️ DISCLAIMER: This model is for educational and portfolio purposes only. It does not constitute investment advice.
